odoo9_addon_account_due_list-9.0.1.0.0-py2.7-nspkg.pth
odoo_addons/account_due_list/init_hook.py
odoo_addons/account_due_list/__openerp__.py
odoo_addons/account_due_list/__init__.py
odoo_addons/account_due_list/README.rst
odoo_addons/account_due_list/migrations/9.0.1.0.0/pre-migration.py
odoo_addons/account_due_list/models/account_move_line.py
odoo_addons/account_due_list/models/__init__.py
odoo_addons/account_due_list/i18n/zh_CN.po
odoo_addons/account_due_list/i18n/pt.po
odoo_addons/account_due_list/i18n/fr_CH.po
odoo_addons/account_due_list/i18n/it.po
odoo_addons/account_due_list/i18n/es.po
odoo_addons/account_due_list/i18n/tr.po
odoo_addons/account_due_list/i18n/hr.po
odoo_addons/account_due_list/i18n/bg.po
odoo_addons/account_due_list/i18n/sl.po
odoo_addons/account_due_list/i18n/pt_PT.po
odoo_addons/account_due_list/i18n/nb.po
odoo_addons/account_due_list/i18n/da.po
odoo_addons/account_due_list/i18n/nl.po
odoo_addons/account_due_list/i18n/de.po
odoo_addons/account_due_list/i18n/fr.po
odoo_addons/account_due_list/i18n/pt_BR.po
odoo_addons/account_due_list/i18n/el_GR.po
odoo_addons/account_due_list/i18n/es_MX.po
odoo_addons/account_due_list/i18n/sk.po
odoo_addons/account_due_list/i18n/fi.po
odoo_addons/account_due_list/views/payment_view.xml
odoo_addons/account_due_list/static/description/icon.png
odoo9_addon_account_due_list-9.0.1.0.0.dist-info/top_level.txt
odoo9_addon_account_due_list-9.0.1.0.0.dist-info/WHEEL
odoo9_addon_account_due_list-9.0.1.0.0.dist-info/RECORD
odoo9_addon_account_due_list-9.0.1.0.0.dist-info/metadata.json
odoo9_addon_account_due_list-9.0.1.0.0.dist-info/DESCRIPTION.rst
odoo9_addon_account_due_list-9.0.1.0.0.dist-info/METADATA
odoo9_addon_account_due_list-9.0.1.0.0.dist-info/namespace_packages.txt
