Metadata-Version: 2.0
Name: odoo9-addon-account-due-list
Version: 9.0.1.0.0
Summary: Payments Due list
Home-page: http://www.agilebg.com
Author: Odoo Community Association (OCA), Agile Business Group, Tecnativa,Zikzakmedia SL
Author-email: support@odoo-community.org
License: AGPL-3
Platform: UNKNOWN
Requires-Dist: odoo (<9.1a,>=9.0a)
Classifier: Programming Language :: Python :: 2.7
Classifier: Framework :: Odoo
Classifier: License :: OSI Approved :: GNU Affero General Public License v3
